akivymd/__init__.py
akivymd/factory_registers.py
akivymd/helper.py
akivymd/tools/__init__.py
akivymd/tools/pyinstaller_hooks.py
akivymd/uix/__init__.py
akivymd/uix/badgelayout.py
akivymd/uix/bottomappbar.py
akivymd/uix/bottomnavigation.py
akivymd/uix/bottomnavigation2.py
akivymd/uix/datepicker.py
akivymd/uix/dialogs.py
akivymd/uix/hintwidget.py
akivymd/uix/imageloader.py
akivymd/uix/imageview.py
akivymd/uix/labelloader.py
akivymd/uix/navigationrail.py
akivymd/uix/onboarding.py
akivymd/uix/piechart.py
akivymd/uix/progressbutton.py
akivymd/uix/progresswidget.py
akivymd/uix/selectionlist.py
akivymd/uix/silverappbar.py
akivymd/uix/spinners.py
akivymd/uix/statusbarcolor.py
akivymd/uix/windows.py
akivymd/uix/behaviors/__init__.py
akivymd/uix/behaviors/addwidget.py
akivymd/uix/behaviors/labelanimation.py
akivymd-1.2.1.dist-info/LICENSE
akivymd-1.2.1.dist-info/METADATA
akivymd-1.2.1.dist-info/WHEEL
akivymd-1.2.1.dist-info/top_level.txt
akivymd-1.2.1.dist-info/RECORD
