Metadata-Version: 2.1
Name: akivymd
Version: 1.2.1
Summary: A set of fancy widgets for KivyMD
Home-page: https://github.com/quitegreensky/akivymd
Author: Sina Namadian
Author-email: quitegreensky@gmail.com
License: MIT
Platform: UNKNOWN
Classifier: Programming Language :: Python :: 3
Classifier: License :: OSI Approved :: MIT License
Requires-Dist: kivymd (>=0.104.1)
Requires-Dist: kivy (>=1.10.1)
